vicpyx/__init__.py
vicpyx/extensions/__init__.py
vicpyx/extensions/extension_base.py
vicpyx/extensions/extension_socket.py
vicpyx/extensions/line_data.py
vicpyx/extensions/point_data.py
vicpyx/vicpy.cp310-win_amd64.pyd
vicpyx-0.5.0.dist-info/METADATA
vicpyx-0.5.0.dist-info/WHEEL
vicpyx-0.5.0.dist-info/licenses/LICENSE
vicpyx-0.5.0.dist-info/RECORD
