Metadata-Version: 2.4
Name: vicpyx
Version: 0.5.0
Summary: The vicpyx module from Correlated Solutions
License-File: LICENSE
Classifier: Programming Language :: Python :: 3
Classifier: Programming Language :: Python :: Implementation :: CPython
Classifier: Operating System :: Unix
Classifier: Operating System :: Microsoft :: Windows
Classifier: Topic :: Software Development
Classifier: Topic :: Scientific/Engineering
Project-URL: homepage, https://correlated.kayako.com/article/55-installing-vicpy
Project-URL: documentation, https://correlated.kayako.com/article/55-installing-vicpy
Requires-Python: >=3.9
Requires-Dist: h5py
Requires-Dist: lxml
Requires-Dist: numpy
Requires-Dist: pillow
Requires-Dist: argparse
